teedoc/__init__.py
teedoc/__main__.py
teedoc/babel.cfg
teedoc/html_parser.py
teedoc/html_renderer.py
teedoc/http_server.py
teedoc/layout_i18n.py
teedoc/locales.cfg
teedoc/logger.py
teedoc/metadata_parser.py
teedoc/plugin.py
teedoc/teedoc_compare.py
teedoc/teedoc_debug.py
teedoc/teedoc_list_files.py
teedoc/teedoc_main.py
teedoc/teedoc_upload.py
teedoc/trans_finish.py
teedoc/trans_prepare.py
teedoc/utils.py
teedoc/version.py
teedoc/locales/ja/LC_MESSAGES/messages.mo
teedoc/locales/ja/LC_MESSAGES/messages.po
teedoc/locales/zh_CN/LC_MESSAGES/messages.mo
teedoc/locales/zh_CN/LC_MESSAGES/messages.po
teedoc/locales/zh_TW/LC_MESSAGES/messages.mo
teedoc/locales/zh_TW/LC_MESSAGES/messages.po
teedoc/static/js/live.js
teedoc/templates/no_translate.md
teedoc/templates/minimal/site_config.json
teedoc/templates/minimal/config/config.json
teedoc/templates/minimal/docs/doc1/README.md
teedoc/templates/minimal/docs/doc1/config.json
teedoc/templates/minimal/docs/doc1/sidebar.yaml
teedoc/templates/minimal/pages/index/404.md
teedoc/templates/minimal/pages/index/README.md
teedoc/templates/minimal/pages/index/config.json
teedoc/templates/minimal/pages/index/favicon.ico
teedoc/templates/minimal/static/css/custom.css
teedoc/templates/minimal/static/js/custom.js
teedoc/templates/template/LICENSE
teedoc/templates/template/README.md
teedoc/templates/template/README_ZH.md
teedoc/templates/template/site_config.json
teedoc/templates/template/assets/action_error.jpg
teedoc/templates/template/assets/action_error_log.jpg
teedoc/templates/template/assets/action_status.jpg
teedoc/templates/template/assets/create_repo.jpg
teedoc/templates/template/assets/github_action.jpg
teedoc/templates/template/assets/github_use_template.jpg
teedoc/templates/template/assets/pages_settings.jpg
teedoc/templates/template/blog/README.md
teedoc/templates/template/blog/config.json
teedoc/templates/template/blog/category1/hello.md
teedoc/templates/template/config/config_en.json
teedoc-1.37.9.dist-info/LICENSE
teedoc-1.37.9.dist-info/METADATA
teedoc-1.37.9.dist-info/WHEEL
teedoc-1.37.9.dist-info/entry_points.txt
teedoc-1.37.9.dist-info/top_level.txt
teedoc-1.37.9.dist-info/RECORD
