Metadata-Version: 2.1
Name: teedoc
Version: 1.37.9
Summary: doc site generator with multiple doc support
Home-page: https://github.com/Neutree/teedoc
Author: Neucrack
Author-email: CZD666666@gmail.com
License: MIT
Keywords: doc website markdown jupyter notbook generator teedoc
Classifier: Intended Audience :: Developers
Classifier: License :: OSI Approved :: MIT License
Classifier: Programming Language :: Python :: 3.7
Classifier: Programming Language :: Python :: 3.8
Classifier: Programming Language :: Python :: 3.9
Classifier: Programming Language :: Python :: 3.10
License-File: LICENSE
Requires-Dist: coloredlogs (>=15.0.1)
Requires-Dist: mistune (<3,>=2.0.3)
Requires-Dist: watchdog (>=2.1.7)
Requires-Dist: nbconvert (>=7.0.0)
Requires-Dist: PyYAML (>=5.4.1)
Requires-Dist: jinja2 (>=3.1.1)
Requires-Dist: flask (>=2.0.2)
Requires-Dist: babel (>=2.9.1)
Requires-Dist: requests
Requires-Dist: progress
Requires-Dist: html2text
